librelingo_audios/__init__.py
librelingo_audios/cli.py
librelingo_audios/functions.py
librelingo_audios/update_audios.py
librelingo_audios-1.3.0.dist-info/WHEEL
librelingo_audios-1.3.0.dist-info/METADATA
librelingo_audios-1.3.0.dist-info/RECORD
