Metadata-Version: 2.1
Name: librelingo-audios
Version: 1.3.0
Summary: Tools to help getting audios for LibreLingo courses
License: GPLv3
Author: Dániel Kántor
Author-email: git@daniel-kantor.com
Requires-Python: >=3.8,<4.0
Classifier: License :: Other/Proprietary License
Classifier: Programming Language :: Python :: 3
Classifier: Programming Language :: Python :: 3.8
Classifier: Programming Language :: Python :: 3.9
Requires-Dist: librelingo-utils (>=2.4.0,<3.0.0)
Requires-Dist: librelingo-yaml-loader (>=1.5.0,<2.0.0)
